anonLLM/__init__.py
anonLLM/anonymizer.py
anonLLM/deanonymizer.py
anonLLM/llm.py
anonLLM-0.1.10.dist-info/METADATA
anonLLM-0.1.10.dist-info/WHEEL
anonLLM-0.1.10.dist-info/top_level.txt
anonLLM-0.1.10.dist-info/RECORD
