Metadata-Version: 2.1
Name: anonLLM
Version: 0.1.10
Summary: Anonymizes personally identifiable information for Large Language Model APIs
Home-page: https://github.com/fsndzomga/anonLLM
Author: FS Ndzomga
Author-email: ndzomgafs@gmail.com
Project-URL: Bug Tracker, https://github.com/fsndzomga/anonLLM/issues
Classifier: Programming Language :: Python :: 3
Classifier: License :: OSI Approved :: MIT License
Classifier: Operating System :: OS Independent
Requires-Python: >=3.6
Requires-Dist: Faker
Requires-Dist: openai
Requires-Dist: pydantic >=2
Requires-Dist: spacy >=3
Provides-Extra: dev
Requires-Dist: pytest ; extra == 'dev'
Requires-Dist: flake8 ; extra == 'dev'
